MANIFEST.in
README.md
pyproject.toml
requirements.txt
setup.cfg
setup.py
t_pom_denticon/__init__.py
t_pom_denticon/exceptions.py
t_pom_denticon/t_denticon.py
t_pom_denticon.egg-info/PKG-INFO
t_pom_denticon.egg-info/SOURCES.txt
t_pom_denticon.egg-info/dependency_links.txt
t_pom_denticon.egg-info/not-zip-safe
t_pom_denticon.egg-info/requires.txt
t_pom_denticon.egg-info/top_level.txt
t_pom_denticon/elements/__init__.py
t_pom_denticon/elements/datetime_element.py
t_pom_denticon/elements/select_element.py
t_pom_denticon/elements/table_row_element.py
t_pom_denticon/elements/text_element.py
t_pom_denticon/pages/__init__.py
t_pom_denticon/pages/login_page.py
t_pom_denticon/pages/offices_list_modal.py
t_pom_denticon/pages/patient_notes_page.py
t_pom_denticon/pages/patient_overview_info_page.py
t_pom_denticon/pages/primary_patient_info_page.py
t_pom_denticon/pages/report_viewer.py
t_pom_denticon/pages/retrieve_dps_report_page.py
t_pom_denticon/pages/retrieve_smart_assist_report_page.py
t_pom_denticon/pages/secondary_patient_info_page.py
t_pom_denticon/pages/update_payer_info.py
tests/test_t_denticon.py