Metadata-Version: 2.1
Name: t_pom_denticon
Version: 0.1.1
Summary: Python package for interacting with denticon portal
Home-page: https://www.thoughtful.ai/
Author: Thoughtful
Author-email: support@thoughtful.ai
Keywords: t_pom_denticon
Classifier: Intended Audience :: Developers
Classifier: Natural Language :: English
Classifier: Programming Language :: Python :: 3
Classifier: Programming Language :: Python :: 3.9
Requires-Python: >=3.9
Requires-Dist: rpaframework==28.6.3
Requires-Dist: t-page-object==0.1.8
